django_easyfilters_ex-0.7.0.dist-info/RECORD
django_easyfilters_ex-0.7.0.dist-info/top_level.txt
django_easyfilters_ex-0.7.0.dist-info/DESCRIPTION.rst
django_easyfilters_ex-0.7.0.dist-info/METADATA
django_easyfilters_ex-0.7.0.dist-info/pydist.json
django_easyfilters_ex-0.7.0.dist-info/WHEEL
django_easyfilters/utils.py
django_easyfilters/__init__.py
django_easyfilters/ranges.py
django_easyfilters/queries.py
django_easyfilters/filters.py
django_easyfilters/models.py
django_easyfilters/filterset.py
django_easyfilters/templates/django_easyfilters/default.html
