Metadata-Version: 2.0
Name: django-easyfilters-ex
Version: 0.7.0
Summary: Easy creation of link-based filtering for a list of Django model objects.
Home-page: https://github.com/ionelmc/django-easyfilters/
Author: Ionel Cristian Mărieș
Author-email: contact@ionelmc.ro
License: MIT
Keywords: django filter autofilter drilldown easy simple
Platform: UNKNOWN
Classifier: Development Status :: 5 - Production/Stable
Classifier: Environment :: Web Environment
Classifier: Intended Audience :: Developers
Classifier: License :: OSI Approved :: MIT License
Classifier: Operating System :: OS Independent
Classifier: Programming Language :: Python :: 2.6
Classifier: Programming Language :: Python :: 2.7
Classifier: Programming Language :: Python :: 3
Classifier: Programming Language :: Python :: 3.3
Classifier: Programming Language :: Python :: 3.4
Classifier: Programming Language :: Python :: Implementation :: CPython
Classifier: Programming Language :: Python :: Implementation :: PyPy
Classifier: Framework :: Django
Classifier: Topic :: Software Development :: User Interfaces
Requires-Dist: Django (>=1.3)
Requires-Dist: python-dateutil
Requires-Dist: six
